Metadata-Version: 2.1
Name: fst-extension
Version: 0.0.0
Summary: Description stub
Author: Jacob Striebel
